{"title":"article","uid":"9f603f4d8f055ec057decaa8865d8462","slug":"article","date":"2021-04-16T09:39:55.000Z","updated":"2021-05-05T14:53:35.442Z","comments":true,"path":"api/articles/article.json","cover":"https://images5.alphacoders.com/678/678402.jpg","content":"<h1 id=\"测试\"><a href=\"#测试\" class=\"headerlink\" title=\"# 测试\"></a># 测试</h1><p>测试一下怎么上传一篇博客</p>\n","text":"# 测试测试一下怎么上传一篇博客 ","link":"","photos":[],"count_time":{"symbolsCount":17,"symbolsTime":"1 mins."},"categories":[],"tags":[],"toc":"<ol class=\"toc\"><li class=\"toc-item toc-level-1\"><a class=\"toc-link\" href=\"#%E6%B5%8B%E8%AF%95\"><span class=\"toc-text\"># 测试</span></a></li></ol>","author":{"name":"JunKai","slug":"blog-author","avatar":"../images/mimir.jpg","link":"/","description":"Keep looking, don't settle.","socials":{"github":"https://github.com/junkaih2019","twitter":"","stackoverflow":"https://stackoverflow.com/users/11885287/dmu-hjk","wechat":"","qq":"","weibo":"https://weibo.com/5015383077/profile?topnav=1&wvr=6","zhihu":"https://www.zhihu.com/people/junkaih","csdn":"https://blog.csdn.net/kaigehuanshi?spm=1000.2115.3001.5343","juejin":"https://juejin.cn/user/3800364449020142","customs":{}}},"mapped":true,"prev_post":{"title":"article","uid":"9f603f4d8f055ec057decaa8865d8462","slug":"article-1","date":"2021-04-16T10:16:23.000Z","updated":"2021-05-05T14:54:12.616Z","comments":true,"path":"api/articles/article-1.json","cover":"https://images2.alphacoders.com/110/1105447.jpg","text":"","link":"","photos":[],"count_time":{"symbolsCount":0,"symbolsTime":"1 mins."},"categories":[],"tags":[],"author":{"name":"JunKai","slug":"blog-author","avatar":"../images/mimir.jpg","link":"/","description":"Keep looking, don't settle.","socials":{"github":"https://github.com/junkaih2019","twitter":"","stackoverflow":"https://stackoverflow.com/users/11885287/dmu-hjk","wechat":"","qq":"","weibo":"https://weibo.com/5015383077/profile?topnav=1&wvr=6","zhihu":"https://www.zhihu.com/people/junkaih","csdn":"https://blog.csdn.net/kaigehuanshi?spm=1000.2115.3001.5343","juejin":"https://juejin.cn/user/3800364449020142","customs":{}}}},"next_post":{}}